MHCSeqNet/MHCSeqNet.py
MHCSeqNet/__init__.py
MHCSeqNet/PretrainedModels/onehot/model_1.h5
MHCSeqNet/PretrainedModels/onehot/model_2.h5
MHCSeqNet/PretrainedModels/onehot/model_3.h5
MHCSeqNet/PretrainedModels/onehot/model_4.h5
MHCSeqNet/PretrainedModels/onehot/model_5.h5
MHCSeqNet/PretrainedModels/onehot/supported_alleles.txt
MHCSeqNet/PretrainedModels/sequence/AlleleInformation.txt
MHCSeqNet/PretrainedModels/sequence/model_1.h5
MHCSeqNet/PretrainedModels/sequence/model_2.h5
MHCSeqNet/PretrainedModels/sequence/model_3.h5
MHCSeqNet/PretrainedModels/sequence/model_4.h5
MHCSeqNet/PretrainedModels/sequence/model_5.h5
MHCSeqNet/PretrainedModels/sequence/supported_alleles.txt
MHCSeqNet/predictor/predictor.py
mhcseqnet-1.1.0.dist-info/METADATA
mhcseqnet-1.1.0.dist-info/WHEEL
mhcseqnet-1.1.0.dist-info/entry_points.txt
mhcseqnet-1.1.0.dist-info/licenses/LICENSE
mhcseqnet-1.1.0.dist-info/RECORD
