Metadata-Version: 2.3
Name: MHCSeqNet
Version: 1.1.0
Summary: MHC ligand prediction tool
Project-URL: Homepage, https://github.com/s3bio/MHCSeqNet/
Project-URL: Issues, https://github.com/s3bio/MHCSeqNet/issues
Author-email: Natapol Pornputtapong <natapol.p@pharm.chula.ac.th>
Classifier: Development Status :: 4 - Beta
Classifier: License :: OSI Approved :: Apache Software License
Classifier: Operating System :: OS Independent
Classifier: Programming Language :: Python :: 3
Classifier: Topic :: Scientific/Engineering :: Bio-Informatics
Requires-Python: >=3.8
Requires-Dist: numpy
Requires-Dist: tensorflow>=2.10.0
